MANIFEST.in
README.md
setup.py
qsa/__init__.py
qsa/__main__.py
qsa/assembler.py
qsa/config.py
qsa/const.py
qsa/spec.py
qsa/cli/__init__.py
qsa/cli/exc.py
qsa/cli/runner.py
qsa/cli/commands/__init__.py
qsa/cli/commands/ignore.py
qsa/cli/commands/init.py
qsa/cli/commands/update.py
qsa/ext/__init__.py
qsa/ext/base.py
qsa/ext/ansible/__init__.py
qsa/ext/ansible/abc.py
qsa/ext/ansible/model.py
qsa/ext/ansible/cli/__init__.py
qsa/ext/ansible/cli/init.py
qsa/ext/ansible/repo/__init__.py
qsa/ext/ansible/repo/playbook.py
qsa/ext/ansible/repo/taglist.py
qsa/ext/ansible/repo/tasklist.py
qsa/ext/ansible/templates/ansible.cfg.j2
qsa/ext/ansible/templates/ci/ansible/main.container-image.yml.j2
qsa/ext/ansible/templates/ci/ansible/playbook.secrets.yml.j2
qsa/ext/ansible/templates/ci/ansible/task.k8s.deployment.yml.j2
qsa/ext/ansible/templates/ci/ansible/task.yml.j2
qsa/ext/ansible/templates/ci/ansible/tasks/ansible.include_tasks.yml.j2
qsa/ext/ansible/templates/ci/ansible/tasks/main.yml.j2
qsa/ext/ansible/templates/ci/jenkins/init.ansible.groovy.j2
qsa/ext/ansible/tests/test_task_from_playbook.py
qsa/ext/app/__init__.py
qsa/ext/app/cli/__init__.py
qsa/ext/autodetect/__init__.py
qsa/ext/ci/__init__.py
qsa/ext/ci/const.py
qsa/ext/ci/schema.py
qsa/ext/ci/templates/Quantumfile.j2
qsa/ext/core/__init__.py
qsa/ext/deployment/__init__.py
qsa/ext/deployment/schema.py
qsa/ext/deployment/model/__init__.py
qsa/ext/deployment/model/deployment.py
qsa/ext/deployment/templates/Quantumfile.j2
qsa/ext/docker/__init__.py
qsa/ext/docker/schema.py
qsa/ext/docker/templates/Dockerfile.base.j2
qsa/ext/docker/templates/Quantumfile.j2
qsa/ext/docker/templates/hadolint.yml.j2
qsa/ext/jenkins/__init__.py
qsa/ext/jenkins/const.py
qsa/ext/jenkins/schema.py
qsa/ext/jenkins/templates/Jenkinsfile.base.j2
qsa/ext/jenkins/templates/Jenkinsfile.container-image.j2
qsa/ext/jenkins/templates/Quantumfile.j2
qsa/ext/jenkins/templates/ci/jenkins/init.base.groovy.j2
quantum_assembler.egg-info/PKG-INFO
quantum_assembler.egg-info/SOURCES.txt
quantum_assembler.egg-info/dependency_links.txt
quantum_assembler.egg-info/entry_points.txt
quantum_assembler.egg-info/requires.txt
quantum_assembler.egg-info/top_level.txt