Metadata-Version: 1.0
Name: quantum-assembler
Version: 1.0.6
Summary: Quantum Service Assembler (QSA)
Home-page: https://www.wizardsofindustry.com
Author: Cochise Ruhulessin
Author-email: cochise.ruhulessin@wizardsofindustry.com
License: UNKNOWN
Platform: UNKNOWN
